gemseo_mlearning/__init__.py
gemseo_mlearning/active_learning/__init__.py
gemseo_mlearning/active_learning/active_learning_algo.py
gemseo_mlearning/active_learning/acquisition_criteria/__init__.py
gemseo_mlearning/active_learning/acquisition_criteria/base_acquisition_criterion.py
gemseo_mlearning/active_learning/acquisition_criteria/base_acquisition_criterion_family.py
gemseo_mlearning/active_learning/acquisition_criteria/base_factory.py
gemseo_mlearning/active_learning/acquisition_criteria/exploration/__init__.py
gemseo_mlearning/active_learning/acquisition_criteria/exploration/base_exploration.py
gemseo_mlearning/active_learning/acquisition_criteria/exploration/distance.py
gemseo_mlearning/active_learning/acquisition_criteria/exploration/exploration.py
gemseo_mlearning/active_learning/acquisition_criteria/exploration/factory.py
gemseo_mlearning/active_learning/acquisition_criteria/exploration/standard_deviation.py
gemseo_mlearning/active_learning/acquisition_criteria/exploration/variance.py
gemseo_mlearning/active_learning/acquisition_criteria/level_set/__init__.py
gemseo_mlearning/active_learning/acquisition_criteria/level_set/base_ei_ef.py
gemseo_mlearning/active_learning/acquisition_criteria/level_set/base_level_set.py
gemseo_mlearning/active_learning/acquisition_criteria/level_set/ef.py
gemseo_mlearning/active_learning/acquisition_criteria/level_set/ei.py
gemseo_mlearning/active_learning/acquisition_criteria/level_set/factory.py
gemseo_mlearning/active_learning/acquisition_criteria/level_set/level_set.py
gemseo_mlearning/active_learning/acquisition_criteria/level_set/u.py
gemseo_mlearning/active_learning/acquisition_criteria/maximum/__init__.py
gemseo_mlearning/active_learning/acquisition_criteria/maximum/_confidence_bound.py
gemseo_mlearning/active_learning/acquisition_criteria/maximum/_expected_impovement.py
gemseo_mlearning/active_learning/acquisition_criteria/maximum/_mean.py
gemseo_mlearning/active_learning/acquisition_criteria/maximum/base_maximum.py
gemseo_mlearning-3.1.0.dist-info/licenses/LICENSE.txt
gemseo_mlearning-3.1.0.dist-info/METADATA
gemseo_mlearning-3.1.0.dist-info/WHEEL
gemseo_mlearning-3.1.0.dist-info/entry_points.txt
gemseo_mlearning-3.1.0.dist-info/top_level.txt
gemseo_mlearning-3.1.0.dist-info/RECORD
