Metadata-Version: 2.4
Name: gemseo-mlearning
Version: 3.1.0
Summary: A GEMSEO extension for machine learning.
Author-email: Matthias De Lozzo <contact@gemseo.org>
License-Expression: LGPL-3.0
Project-URL: Homepage, https://gemseo.org
Project-URL: Source, https://gitlab.com/gemseo/dev/gemseo-mlearning
Project-URL: Issues, https://gitlab.com/gemseo/dev/gemseo-mlearning/-/issues
Classifier: Intended Audience :: Science/Research
Classifier: Topic :: Scientific/Engineering
Classifier: Operating System :: POSIX :: Linux
Classifier: Operating System :: MacOS
Classifier: Operating System :: Microsoft :: Windows
Classifier: Programming Language :: Python :: 3 :: Only
Classifier: Programming Language :: Python :: 3.10
Classifier: Programming Language :: Python :: 3.11
Classifier: Programming Language :: Python :: 3.12
Classifier: Programming Language :: Python :: 3.13
Requires-Python: <3.14,>=3.10
License-File: LICENSE.txt
Requires-Dist: gemseo[all]<7,>=6.3
Requires-Dist: numpy
Requires-Dist: openturns<1.25
Requires-Dist: scikit-learn
Requires-Dist: scipy
Requires-Dist: smt[gpx]<=2.9.5,>=2.5.0
Dynamic: license-file
